triko/__init__.py
triko/config.py
triko/encoders.py
triko/triko.py
triko/types.py
triko-0.0.1.dist-info/METADATA
triko-0.0.1.dist-info/WHEEL
triko-0.0.1.dist-info/top_level.txt
triko-0.0.1.dist-info/RECORD
