Metadata-Version: 2.1
Name: triko
Version: 0.0.1
Summary: Simplifies a process of encoding/decoding data using TFRecord framework.
Home-page: https://github.com/ityutin/triko
Author: Ilya Tyutin
Author-email: emmarrgghh@gmail.com
License: MIT
Platform: UNKNOWN
Classifier: License :: OSI Approved :: MIT License
Classifier: Programming Language :: Python :: 3
Classifier: Programming Language :: Python :: 3.7
Requires-Dist: tensorflow
Requires-Dist: numpy
